crimsonslate_tools/__init__.py
crimsonslate_tools/admin.py
crimsonslate_tools/apps.py
crimsonslate_tools/models.py
crimsonslate_tools/tests.py
crimsonslate_tools/templates/crimsonslate_tools/layout.html
crimsonslate_tools/templates/crimsonslate_tools/tests/test_htmx_template_response.html
crimsonslate_tools/templates/crimsonslate_tools/tests/partials/_test_htmx_template_response.html
crimsonslate_tools/views/__init__.py
crimsonslate_tools/views/mixins.py
crimsonslate_tools-1.0.1.dist-info/METADATA
crimsonslate_tools-1.0.1.dist-info/WHEEL
crimsonslate_tools-1.0.1.dist-info/licenses/COPYING
crimsonslate_tools-1.0.1.dist-info/RECORD
