Metadata-Version: 2.4
Name: crimsonslate-tools
Version: 1.0.1
Summary: Django project dev tools by crimsonslate
Project-URL: Homepage, https://github.com/crimsonslate/tools
Project-URL: Repository, https://github.com/crimsonslate/tools
Project-URL: Documentation, https://crimsonslate-tools.readthedocs.io/en/latest
Author-email: Blake Nall <dev@darthnall.com>, Constantine Kapatos <kapatos.constantine@gmail.com>
License-File: COPYING
Classifier: License :: OSI Approved :: GNU General Public License v3 or later (GPLv3+)
Classifier: Operating System :: OS Independent
Classifier: Programming Language :: Python :: 3
Classifier: Programming Language :: Python :: 3.13
Requires-Python: >=3.13
Requires-Dist: django>=5.2.1
